{
    "name": "AlertHistory",
    "fields": [
        {
            "fieldName": "subject",
            "fieldType": "String"
        },
        {
            "fieldName": "message",
            "fieldType": "String"
        },
        {
            "fieldName": "emailStatus",
            "fieldType": "Boolean"
        },
        {
            "fieldName": "webSocketStatus",
            "fieldType": "Boolean"
        },
        {
            "fieldName": "smsStatus",
            "fieldType": "Boolean"
        },
        {
            "fieldName": "webSockectRead",
            "fieldType": "Boolean"
        },
        {
            "fieldName": "retryAttempts",
            "fieldType": "Integer"
        },
        {
            "fieldName": "errorLog",
            "fieldType": "String"
        },
        {
            "fieldName": "receipientEmail",
            "fieldType": "String"
        },
        {
            "fieldName": "userId",
            "fieldType": "Long"
        }
    ],
    "relationships": [
        {
            "relationshipType": "many-to-one",
            "otherEntityName": "triggeredAlert",
            "otherEntityRelationshipName": "alertHistory",
            "relationshipName": "triggeredAlert",
            "otherEntityField": "id"
        }
    ],
    "changelogDate": "20201130180025",
    "entityTableName": "alert_history",
    "dto": "no",
    "pagination": "no",
    "service": "no",
    "jpaMetamodelFiltering": false,
    "fluentMethods": true,
    "readOnly": false,
    "clientRootFolder": "alerting",
    "applications": "*",
    "microserviceName": "alerting"
}